azure/mgmt/managementpartner/__init__.py
azure/mgmt/managementpartner/_ace_provisioning_management_partner_api.py
azure/mgmt/managementpartner/_configuration.py
azure/mgmt/managementpartner/_version.py
azure/mgmt/managementpartner/aio/__init__.py
azure/mgmt/managementpartner/aio/_ace_provisioning_management_partner_api.py
azure/mgmt/managementpartner/aio/_configuration.py
azure/mgmt/managementpartner/aio/operations/__init__.py
azure/mgmt/managementpartner/aio/operations/_operation_operations.py
azure/mgmt/managementpartner/aio/operations/_partner_operations.py
azure/mgmt/managementpartner/aio/operations/_partners_operations.py
azure/mgmt/managementpartner/models/__init__.py
azure/mgmt/managementpartner/models/_ace_provisioning_management_partner_api_enums.py
azure/mgmt/managementpartner/models/_models.py
azure/mgmt/managementpartner/models/_models_py3.py
azure/mgmt/managementpartner/operations/__init__.py
azure/mgmt/managementpartner/operations/_operation_operations.py
azure/mgmt/managementpartner/operations/_partner_operations.py
azure/mgmt/managementpartner/operations/_partners_operations.py
azure_mgmt_managementpartner-1.0.0.dist-info/METADATA
azure_mgmt_managementpartner-1.0.0.dist-info/WHEEL
azure_mgmt_managementpartner-1.0.0.dist-info/top_level.txt
azure_mgmt_managementpartner-1.0.0.dist-info/RECORD
